{"modules": {
  "normalize":            true,
  "print":                false,

  "scaffolding":          true,
  "type":                 true,
  "code":                 true,
  "grid":                 true,
  "tables":               true,
  "forms":                true,
  "buttons":              true,

  "glyphicons":           false,
  "button-groups":        true,
  "input-groups":         true,
  "navs":                 true,
  "navbar":               true,
  "breadcrumbs":          false,
  "pagination":           false,
  "pager":                false,
  "labels":               true,
  "badges":               false,
  "jumbotron":            false,
  "thumbnails":           false,
  "alerts":               false,
  "progress-bars":        false,
  "media":                false,
  "list-group":           true,
  "panels":               true,
  "wells":                true,
  "close":                false,

  "component-animations": false,
  "dropdowns":            false,
  "modals":               false,
  "tooltip":              false,
  "popovers":             false,
  "carousel":             false,

  "affix":                false,
  "alert":                false,
  "button":               false,
  "collapse":             false,
  "scrollspy":            false,
  "tab":                  false,
  "transition":           false,

  "utilities":            false,
  "responsive-utilities": false
  }}
